{
    "pools": [
        {
            "rolls": 1,
            "entries": [
                {
                    "type": "item",
                    "name": "jedy:summon_shukaku",
                    "weight": 1,
                    "functions": [
                        {
                            "function": "set_count",
                            "count": {
                                "min": 1,
                                "max": 1                           }
                        },
                        {
                            "function": "looting_enchant",
                            "count": {
                                "min": 1,
                                "max": 1                           }
                        }
                    ]
                }
            ]
        },
        {
            "rolls": 1,
            "entries": [
                {
                    "type": "item",
                    "name": "jedy:summon_matatabi",
                    "weight": 1,
                    "functions": [
                        {
                            "function": "set_count",
                            "count": {
                                "min": 1,
                                "max": 1
                            }
                        },
                        {
                            "function": "looting_enchant",
                            "count": {
                                "min": 1,
                                "max": 1
                            }
                        }
                    ]
                }
            ]
        },
        {
            "rolls": 1,
            "entries": [
                {
                    "type": "item",
                    "name": "jedy:summon_isobu",
                    "weight": 1,
                    "functions": [
                        {
                            "function": "set_count",
                            "count": {
                                "min": 1,
                                "max": 1
                            }
                        },
                        {
                            "function": "looting_enchant",
                            "count": {
                                "min": 1,
                                "max": 1
}
                        }
                    ]
                }
            ]
        },
        {
            "rolls": 1,
            "entries": [
                {
                    "type": "item",
                    "name": "jedy:summon_songoku",
                    "weight": 1,
                    "functions": [
                        {
                            "function": "set_count",
                            "count": {
                                "min": 1,
                                "max": 1                           }
                        },
                        {
                            "function": "looting_enchant",
                            "count": {
                                "min": 1,
                                "max": 1                          }
                        }
                    ]
                }
            ]
        },
        {
            "rolls": 1,
            "entries": [
                {
                    "type": "item",
                    "name": "jedy:summon_kokuo",
                    "weight": 1,
                    "functions": [
                        {
                            "function": "set_count",
                            "count": {
                                "min": 1,
                                "max": 1
                            }
                        },
                        {
                            "function": "looting_enchant",
                            "count": {
                                "min": 1,
                                "max": 1
                            }
                        }
                    ]
                }
            ]
        },
        {
            "rolls": 1,
            "entries": [
                {
                    "type": "item",
                    "name": "jedy:summon_saiken",
                    "weight": 1,
                    "functions": [
                        {
                            "function": "set_count",
                            "count": {
                                "min": 1,
                                "max": 1
                            }
                        },
                        {
                            "function": "looting_enchant",
                            "count": {
                                "min": 1,
                                "max": 1
                            }
                        }
                    ]
                }
            ]
                },
                {
            "rolls": 1,
            "entries": [
                {
                    "type": "item",
                    "name": "jedy:summon_choumei",
                    "weight": 1,
                    "functions": [
                        {
                            "function": "set_count",
                            "count": {
                                "min": 1,
                                "max": 1                           }
                        },
                        {
                            "function": "looting_enchant",
                            "count": {
                                "min": 1,
                                "max": 1                           }
                        }
                    ]
                }
            ]
        },
        {
            "rolls": 1,
            "entries": [
                {
                    "type": "item",
                    "name": "jedy:summon_gyuki",
                    "weight": 1,
                    "functions": [
                        {
                            "function": "set_count",
                            "count": {
                                "min": 1,
                                "max": 1
                            }
                        },
                        {
                            "function": "looting_enchant",
                            "count": {
                                "min": 1,
                                "max": 1
                            }
                        }
                    ]
                }
            ]
        },
        {
            "rolls": 1,
            "entries": [
                {
                    "type": "item",
                    "name": "jedy:summon_kurama",
                    "weight": 1,
                    "functions": [
                        {
                            "function": "set_count",
                            "count": {
                                "min": 1,
                                "max": 1
                            }
                        },
                        {
                            "function": "looting_enchant",
                            "count": {
                                "min": 1,
                                "max": 1
                            }
                        }
                    ]
                }
            ]
        }
    ]
}